fryweb/__init__.py
fryweb/__main__.py
fryweb/admin.py
fryweb/apps.py
fryweb/cmdline.py
fryweb/config.py
fryweb/element.py
fryweb/fileiter.py
fryweb/models.py
fryweb/page.py
fryweb/reload.py
fryweb/signals.py
fryweb/spec.py
fryweb/urls.py
fryweb/utils.py
fryweb/views.py
fryweb/css/__init__.py
fryweb/css/collector.py
fryweb/css/color.py
fryweb/css/generator.py
fryweb/css/modifiers.py
fryweb/css/plugin.py
fryweb/css/preflight.css
fryweb/css/style.py
fryweb/css/utilities.py
fryweb/fry/__init__.py
fryweb/fry/base.py
fryweb/fry/fry.ppeg
fryweb/fry/frylexer.py
fryweb/fry/fryloader.py
fryweb/fry/generator.py
fryweb/fry/grammar.py
fryweb/js/__init__.py
fryweb/js/generator.py
fryweb/management/__init__.py
fryweb/management/commands/__init__.py
fryweb/management/commands/fryhcs.py
fryweb/migrations/__init__.py
fryweb/static/js/fryweb.js
fryweb-0.3.11.dist-info/METADATA
fryweb-0.3.11.dist-info/WHEEL
fryweb-0.3.11.dist-info/entry_points.txt
fryweb-0.3.11.dist-info/licenses/LICENSE
fryweb-0.3.11.dist-info/RECORD
