Metadata-Version: 2.4
Name: fryweb
Version: 0.3.11
Summary: A asgi/wsgi server that can generate HTML, Javascript and CSS, based on fry file
Project-URL: Homepage, https://github.com/frybox/fryweb
Project-URL: Bug Tracker, https://github.com/frybox/fryweb/issues
Project-URL: Source, https://github.com/frybox/fryweb
Author-email: Zenk Ju <juzejian@gmail.com>
License-Expression: MIT
License-File: LICENSE
Keywords: asgi,fryweb,fw,server,wsgi
Classifier: License :: OSI Approved :: MIT License
Classifier: Operating System :: OS Independent
Classifier: Programming Language :: Python :: 3
Requires-Python: >=3.8
Requires-Dist: click
Requires-Dist: coloraide
Requires-Dist: parsimonious
Requires-Dist: psutil
Requires-Dist: starlette
Requires-Dist: uvicorn
